LICENSE.txt
MANIFEST.in
README.rst
setup.cfg
setup.py
amqpconsumer/__init__.py
amqpconsumer/events.py
amqpconsumer.egg-info/PKG-INFO
amqpconsumer.egg-info/SOURCES.txt
amqpconsumer.egg-info/dependency_links.txt
amqpconsumer.egg-info/requires.txt
amqpconsumer.egg-info/top_level.txt