Metadata-Version: 1.1
Name: amqpconsumer
Version: 1.7
Summary: AMQP event listener
Home-page: https://github.com/ByteInternet/amqpconsumer
Author: Byte B.V.
Author-email: tech@byte.nl
License: 3-clause BSD
Keywords: amqp events consumer listener rabbitmq
Platform: UNKNOWN
Classifier: Development Status :: 5 - Production/Stable
Classifier: License :: OSI Approved :: BSD License
Classifier: Intended Audience :: Developers
Classifier: Topic :: Utilities
Classifier: Topic :: Communications
Classifier: Topic :: Internet
Classifier: Programming Language :: Python :: 2
Classifier: Programming Language :: Python :: 2.7
Classifier: Programming Language :: Python :: 3
Classifier: Programming Language :: Python :: 3.4
Classifier: Programming Language :: Python :: 3.5
Classifier: Programming Language :: Python :: 3.6
